{
  "Workflows": [
    {
      "Path": null,
      "SortBy": 0,
      "VariablesSectionElementsOrder": [],
      "ArgumentsSectionElementsOrder": [
        "IO_Present_URL"
      ],
      "ConstantsSectionElementsOrder": [],
      "AddedNamespaces": null
    },
    {
      "Path": "LoginTestCase1.xaml",
      "SortBy": 0,
      "VariablesSectionElementsOrder": [
        "Errormsg&Sequence_2"
      ],
      "ArgumentsSectionElementsOrder": [],
      "ConstantsSectionElementsOrder": [],
      "AddedNamespaces": null
    },
    {
      "Path": "LoginTestCase2.xaml",
      "SortBy": 0,
      "VariablesSectionElementsOrder": [
        "Switch&Sequence_2",
        "SwitchMode&Sequence_2",
        "LoginText&Sequence_2",
        "Errormsg&Sequence_2"
      ],
      "ArgumentsSectionElementsOrder": [],
      "ConstantsSectionElementsOrder": [],
      "AddedNamespaces": null
    },
    {
      "Path": "ROTC_001.xaml",
      "SortBy": 0,
      "VariablesSectionElementsOrder": [
        "Switch&Sequence_1",
        "SwitchMode&Sequence_1",
        "LoginText&Sequence_1",
        "OrderEntry&Sequence_1",
        "OrderScreen&Sequence_1",
        "DTOrder_Str&Sequence_1",
        "Exception&Sequence_1",
        "Row&Sequence_1",
        "DTOrder&Sequence_1",
        "Errormsg&Sequence_1",
        "Ver_Result_Bool&Sequence_1",
        "Output_msg&Sequence_1",
        "ItemDescription&Sequence_29"
      ],
      "ArgumentsSectionElementsOrder": [
        "IO_present_URL",
        "Errormsg",
        "UserName",
        "PassWord"
      ],
      "ConstantsSectionElementsOrder": [],
      "AddedNamespaces": null
    },
    {
      "Path": "ROTC_003.xaml",
      "SortBy": 0,
      "VariablesSectionElementsOrder": [
        "Output_msg&Sequence_1",
        "DTOrder&Sequence_1",
        "Qnt_Error_Msg&Sequence_1",
        "Errormsg&Sequence_1",
        "OrderScreen&Sequence_1",
        "Exception&Sequence_1",
        "Error_Array&Sequence_1",
        "Row&Sequence_1",
        "TestCase&Sequence_1",
        "Ver_Result_Bool&Sequence_1"
      ],
      "ArgumentsSectionElementsOrder": [],
      "ConstantsSectionElementsOrder": [],
      "AddedNamespaces": null
    },
    {
      "Path": "ROTC_002.xaml",
      "SortBy": 0,
      "VariablesSectionElementsOrder": [
        "Output_msg&Sequence_1",
        "Ver_Result_Bool&Sequence_1",
        "Row&Sequence_1",
        "Errormsg&Sequence_1",
        "Exception&Sequence_1",
        "dtstoreIDstr&Sequence_1",
        "DTOrder&Sequence_1",
        "OrderScreen&Sequence_1",
        "ItemDescription&Sequence_38"
      ],
      "ArgumentsSectionElementsOrder": [],
      "ConstantsSectionElementsOrder": [],
      "AddedNamespaces": null
    },
    {
      "Path": "ROTC_004.xaml",
      "SortBy": 0,
      "VariablesSectionElementsOrder": [
        "Output_msg&Sequence_1",
        "Errormsg&Sequence_1",
        "Array_Error&Sequence_1",
        "SellValue&Sequence_1",
        "DTOrder&Sequence_1",
        "OrderScreen&Sequence_1",
        "Exception&Sequence_1",
        "Row&Sequence_1",
        "Price_Errormsg&Sequence_1",
        "TestCase&Sequence_1",
        "Ver_Result_bool&Sequence_1",
        "ItemDescription&Sequence_31"
      ],
      "ArgumentsSectionElementsOrder": [],
      "ConstantsSectionElementsOrder": [],
      "AddedNamespaces": null
    },
    {
      "Path": "ROTC_005.xaml",
      "SortBy": 0,
      "VariablesSectionElementsOrder": [
        "Ver_Result_Bool&Sequence_1",
        "Output_msg&Sequence_1",
        "Checked&Sequence_3",
        "OutputMsg&Sequence_1",
        "internal_toggle&Sequence_1",
        "WMS_check_box&Sequence_4",
        "Row&Sequence_1",
        "TestCase&Sequence_1",
        "Exception&Sequence_1",
        "OrderStatus&Sequence_1",
        "DTOrder&Sequence_1"
      ],
      "ArgumentsSectionElementsOrder": [],
      "ConstantsSectionElementsOrder": [],
      "AddedNamespaces": null
    },
    {
      "Path": "ROTC_006.xaml",
      "SortBy": 0,
      "VariablesSectionElementsOrder": [
        "Ver_Result_Bool&Sequence_1",
        "Output_msg&Sequence_1",
        "internal_toggle&Sequence_1",
        "Row&Sequence_1",
        "Exception&Sequence_1",
        "OrderType&Sequence_1",
        "ItemDesc&Sequence_1",
        "Errormsg&Sequence_1",
        "DTOrder&Sequence_1"
      ],
      "ArgumentsSectionElementsOrder": [],
      "ConstantsSectionElementsOrder": [],
      "AddedNamespaces": null
    },
    {
      "Path": "ROTC_007.xaml",
      "SortBy": 0,
      "VariablesSectionElementsOrder": [
        "Exception&Sequence_49",
        "DTOrder_1&Sequence_49",
        "dtstoreIDstr&Sequence_49",
        "Output_msg&Sequence_23",
        "Ver_Result_Bool&Sequence_23",
        "Row&Sequence_23",
        "Exception&Sequence_23",
        "internal_toggle&Sequence_23",
        "DTOrder&Sequence_23",
        "Errormsg&Sequence_7"
      ],
      "ArgumentsSectionElementsOrder": [
        "IO_present_URL"
      ],
      "ConstantsSectionElementsOrder": [],
      "AddedNamespaces": null
    },
    {
      "Path": "ROTC_008.xaml",
      "SortBy": 0,
      "VariablesSectionElementsOrder": [
        "Ver_Result_Bool&Sequence_1",
        "Output_msg&Sequence_1",
        "Row&Sequence_1",
        "Exception&Sequence_1",
        "ItemDescription&Sequence_3",
        "AC_Value&Sequence_1",
        "SellValue&Sequence_5",
        "DTOrder&Sequence_1",
        "Qnt_Errormsg&Sequence_2",
        "Errormsg&Sequence_2"
      ],
      "ArgumentsSectionElementsOrder": [],
      "ConstantsSectionElementsOrder": [],
      "AddedNamespaces": null
    },
    {
      "Path": "TestCase.xaml",
      "SortBy": 0,
      "VariablesSectionElementsOrder": [
        "internal_toggle&Sequence_1",
        "OutputMsg&Sequence_1",
        "OrderStatus&Sequence_1",
        "OSP_App_Res&Sequence_1",
        "Errormsg&Sequence_54",
        "Excel_File_Path&Sequence_1",
        "Exception&Sequence_1",
        "OrderType&Sequence_1",
        "UserName&Sequence_1",
        "PassWord&Sequence_1"
      ],
      "ArgumentsSectionElementsOrder": [
        "DTOrder"
      ],
      "ConstantsSectionElementsOrder": [],
      "AddedNamespaces": null
    },
    {
      "Path": "Ep.xaml",
      "SortBy": 0,
      "VariablesSectionElementsOrder": [
        "DataRow&Sequence_1",
        "Emails&Sequence_1",
        "BrowserData&Sequence_1"
      ],
      "ArgumentsSectionElementsOrder": [
        "IO_Present_URL"
      ],
      "ConstantsSectionElementsOrder": [],
      "AddedNamespaces": null
    },
    {
      "Path": "ROTC_009.xaml",
      "SortBy": 0,
      "VariablesSectionElementsOrder": [
        "Ver_Result_Bool&Sequence_1",
        "Output_msg&Sequence_1",
        "Errormsg&Sequence_1",
        "Price_Errormsg&Sequence_1",
        "ItemDescription&Sequence_34",
        "Row&Sequence_1",
        "Exception&Sequence_1",
        "FoundElement&Sequence_1",
        "Warning&Sequence_1",
        "Sell_D&Sequence_1",
        "SellValue&Sequence_1",
        "DTOrder&Sequence_1",
        "TestCase&Sequence_1",
        "Qnt_Errormsg&Sequence_4",
        "ItemDescription&Sequence_5"
      ],
      "ArgumentsSectionElementsOrder": [],
      "ConstantsSectionElementsOrder": [],
      "AddedNamespaces": null
    },
    {
      "Path": "ExceptionHandle.xaml",
      "SortBy": 0,
      "VariablesSectionElementsOrder": [
        "Password&Sequence_1",
        "UserName&Sequence_1",
        "URL&Sequence_1",
        "Out_Config&Sequence_1",
        "configDT&Sequence_1",
        "SheetName&Sequence_1",
        "ConfigFile&Sequence_1",
        "EnvUrlName&Sequence_1",
        "present_url&Sequence_1",
        "Int&Sequence_1",
        "Array&Sequence_6",
        "Row&Sequence_1",
        "Dt_1&Sequence_10",
        "Exception&Sequence_1",
        "DTOrder_1&Sequence_1",
        "dtstoreIDstr&Sequence_1"
      ],
      "ArgumentsSectionElementsOrder": [],
      "ConstantsSectionElementsOrder": [],
      "AddedNamespaces": null
    },
    {
      "Path": "ROTC_010.xaml",
      "SortBy": 0,
      "VariablesSectionElementsOrder": [
        "Ver_Result_Bool&Sequence_1",
        "Exception&Sequence_1",
        "Errormsg&Sequence_1",
        "Row&Sequence_1",
        "TestCase&Sequence_1",
        "Output_msg&Sequence_1",
        "ItemDesc&Sequence_1",
        "DTOrder&Sequence_1"
      ],
      "ArgumentsSectionElementsOrder": [],
      "ConstantsSectionElementsOrder": [],
      "AddedNamespaces": null
    },
    {
      "Path": "ROTC_011.xaml",
      "SortBy": 0,
      "VariablesSectionElementsOrder": [
        "Ver_Result_Bool&Sequence_1",
        "Statusmsg&Sequence_1",
        "Row&Sequence_31",
        "Exception&Sequence_1",
        "Errormsg&Sequence_1",
        "Output_msg&Sequence_1",
        "Cycle_value&Sequence_1",
        "TestCase&Sequence_1",
        "DTOrder&Sequence_1"
      ],
      "ArgumentsSectionElementsOrder": [],
      "ConstantsSectionElementsOrder": [],
      "AddedNamespaces": null
    },
    {
      "Path": "ROTC_012.xaml",
      "SortBy": 0,
      "VariablesSectionElementsOrder": [
        "Output_msg&Sequence_1",
        "DTOrder&Sequence_1",
        "OrderScreen&Sequence_1",
        "Errormsg&Sequence_1",
        "Ver_Result_Bool&Sequence_1",
        "Exception&Sequence_1",
        "Row&Sequence_1",
        "ItemDescription&Sequence_2"
      ],
      "ArgumentsSectionElementsOrder": [],
      "ConstantsSectionElementsOrder": [],
      "AddedNamespaces": null
    },
    {
      "Path": "ROTC_013.xaml",
      "SortBy": 0,
      "VariablesSectionElementsOrder": [
        "Output_msg&Sequence_1",
        "DTOrder&Sequence_1",
        "OrderScreen&Sequence_1",
        "Errormsg&Sequence_1",
        "Ver_Result_Bool&Sequence_1",
        "Exception&Sequence_1",
        "ItemDescription&Sequence_6",
        "ItemDescription&Sequence_2",
        "Row&Sequence_25"
      ],
      "ArgumentsSectionElementsOrder": [],
      "ConstantsSectionElementsOrder": [],
      "AddedNamespaces": null
    },
    {
      "Path": "Ep1.xaml",
      "SortBy": 0,
      "VariablesSectionElementsOrder": [
        "Pricing_Method&Sequence_20",
        "Array&Sequence_1",
        "OrderScreen&Sequence_1"
      ],
      "ArgumentsSectionElementsOrder": [
        "IO_Present_URL"
      ],
      "ConstantsSectionElementsOrder": [],
      "AddedNamespaces": null
    },
    {
      "Path": "TC_004.xaml",
      "SortBy": 0,
      "VariablesSectionElementsOrder": [
        "Errormsg&Sequence_1",
        "SellValue&Sequence_1",
        "Price_Errormsg&Sequence_1",
        "Array_Error&Sequence_1",
        "ItemDescription&Sequence_2"
      ],
      "ArgumentsSectionElementsOrder": [
        "IO_Present_URL",
        "I_Division",
        "I_Company",
        "I_OrderType",
        "I_Customer",
        "I_ItemCode",
        "I_Qty",
        "I_SellPrice",
        "I_PO",
        "I_Route",
        "O_Output_msg",
        "O_Ver_Result_Bool"
      ],
      "ConstantsSectionElementsOrder": [],
      "AddedNamespaces": null
    },
    {
      "Path": "TC_001.xaml",
      "SortBy": 0,
      "VariablesSectionElementsOrder": [
        "Errormsg&Sequence_1",
        "OrderScreen&Sequence_1",
        "ItemDescription&Sequence_5"
      ],
      "ArgumentsSectionElementsOrder": [
        "IO_Present_URL",
        "I_Division",
        "I_Company",
        "I_OrderType",
        "I_Customer",
        "I_ItemCode",
        "I_Qty",
        "I_SellPrice",
        "I_PO",
        "I_Route",
        "O_Output_msg",
        "O_Ver_Result_Bool"
      ],
      "ConstantsSectionElementsOrder": [],
      "AddedNamespaces": null
    },
    {
      "Path": "TC_002.xaml",
      "SortBy": 0,
      "VariablesSectionElementsOrder": [
        "Errormsg&Sequence_1",
        "OrderScreen&Sequence_1",
        "Present_URL&Sequence_18",
        "ItemDescription&Sequence_2"
      ],
      "ArgumentsSectionElementsOrder": [
        "I_Company",
        "I_Division",
        "I_OrderType",
        "I_Customer",
        "I_ItemCode",
        "I_Qty",
        "I_SellPrice",
        "O_Output_msg",
        "O_Ver_Result_Bool",
        "IO_Present_URL",
        "I_PO",
        "I_Route"
      ],
      "ConstantsSectionElementsOrder": [],
      "AddedNamespaces": null
    },
    {
      "Path": "TC_003.xaml",
      "SortBy": 0,
      "VariablesSectionElementsOrder": [
        "Qnt_Error_Msg&Sequence_1",
        "Errormsg&Sequence_1",
        "Error_Array&Sequence_1"
      ],
      "ArgumentsSectionElementsOrder": [
        "IO_Present_URL",
        "I_Division",
        "I_Company",
        "I_OrderType",
        "I_Customer",
        "I_ItemCode",
        "I_Qty",
        "I_SellPrice",
        "I_PO",
        "I_Route",
        "O_Output_msg",
        "O_Ver_Result_Bool"
      ],
      "ConstantsSectionElementsOrder": [],
      "AddedNamespaces": null
    },
    {
      "Path": "TC_005.xaml",
      "SortBy": 0,
      "VariablesSectionElementsOrder": [
        "OrderStatus&Sequence_1",
        "internal_toggle&Sequence_1",
        "WMS_check_box&Sequence_3"
      ],
      "ArgumentsSectionElementsOrder": [
        "I_OrderType",
        "I_SellPrice",
        "IO_Present_URL",
        "O_Ver_Result_Bool",
        "I_Route",
        "I_PO",
        "I_Qty",
        "I_ItemCode",
        "I_Customer",
        "O_Output_msg",
        "I_Company",
        "I_Division"
      ],
      "ConstantsSectionElementsOrder": [],
      "AddedNamespaces": null
    },
    {
      "Path": "TC_006.xaml",
      "SortBy": 0,
      "VariablesSectionElementsOrder": [
        "Errormsg&Sequence_1",
        "internal_toggle&Sequence_1"
      ],
      "ArgumentsSectionElementsOrder": [
        "I_Route",
        "IO_Present_URL",
        "I_OrderType",
        "I_SellPrice",
        "I_PO",
        "O_Ver_Result_Bool",
        "I_Qty",
        "I_ItemCode",
        "I_Customer",
        "O_Output_msg",
        "I_Company",
        "I_Division"
      ],
      "ConstantsSectionElementsOrder": [],
      "AddedNamespaces": null
    },
    {
      "Path": "TC_007.xaml",
      "SortBy": 0,
      "VariablesSectionElementsOrder": [
        "internal_toggle&Sequence_1",
        "Errormsg&Sequence_2"
      ],
      "ArgumentsSectionElementsOrder": [
        "IO_Present_URL",
        "I_OrderType",
        "I_PO",
        "I_Route",
        "I_SellPrice",
        "I_Qty",
        "I_ItemCode",
        "I_Customer",
        "Ver_Result_Bool",
        "Output_msg",
        "I_Company",
        "I_Division"
      ],
      "ConstantsSectionElementsOrder": [],
      "AddedNamespaces": null
    },
    {
      "Path": "LogOutTC.xaml",
      "SortBy": 0,
      "VariablesSectionElementsOrder": [],
      "ArgumentsSectionElementsOrder": [
        "IO_Present_URL"
      ],
      "ConstantsSectionElementsOrder": [],
      "AddedNamespaces": null
    },
    {
      "Path": "TC_008.xaml",
      "SortBy": 0,
      "VariablesSectionElementsOrder": [
        "AC_Value&Sequence_1",
        "Qnt_Errormsg&Sequence_2",
        "Errormsg&Sequence_2",
        "SellValue&Sequence_3",
        "ItemDescription&Sequence_4"
      ],
      "ArgumentsSectionElementsOrder": [
        "I_Route",
        "I_PO",
        "I_SellPrice",
        "I_Qty",
        "Ver_Result_Bool",
        "Output_msg",
        "I_ItemCode",
        "I_Customer",
        "I_OrderType",
        "I_Company",
        "I_Division",
        "IO_Present_URL"
      ],
      "ConstantsSectionElementsOrder": [],
      "AddedNamespaces": null
    },
    {
      "Path": "TC_009.xaml",
      "SortBy": 0,
      "VariablesSectionElementsOrder": [
        "Price_Errormsg&Sequence_22",
        "Warning&Sequence_19",
        "FoundElement&Sequence_19",
        "SellValue&Sequence_1",
        "Sell_D&Sequence_1",
        "Qnt_Errormsg&Sequence_2",
        "ItemDescription&Sequence_3",
        "ItemDescription&Sequence_4"
      ],
      "ArgumentsSectionElementsOrder": [
        "Ver_Result_Bool",
        "Output_msg",
        "Warning",
        "I_Qty",
        "I_ItemCode",
        "I_Customer",
        "I_OrderType",
        "I_Company",
        "I_Division",
        "IO_Present_URL"
      ],
      "ConstantsSectionElementsOrder": [],
      "AddedNamespaces": null
    },
    {
      "Path": "Flowchart.xaml",
      "SortBy": 0,
      "VariablesSectionElementsOrder": [],
      "ArgumentsSectionElementsOrder": [],
      "ConstantsSectionElementsOrder": [],
      "AddedNamespaces": null
    },
    {
      "Path": "TC_072_Inquire_Billing_Icon.xaml",
      "SortBy": 0,
      "VariablesSectionElementsOrder": [
        "OrderScreen&Sequence_1",
        "tempURL&Sequence_1",
        "ExtractDataTable&Sequence_1",
        "ChildrenValues&Sequence_1",
        "ExtractedTable&Sequence_1",
        "checkVar&Sequence_14",
        "ItemDescription&Sequence_3",
        "NewTab&Sequence_36",
        "newTabUrl&Sequence_36",
        "Array2&Sequence_36",
        "Department1&Sequence_36",
        "Department2&Sequence_36",
        "Department5&Sequence_36",
        "Department6&Sequence_36",
        "Department3&Sequence_36",
        "Department4&Sequence_36",
        "Array&Sequence_98",
        "ItemDescription&Sequence_37",
        "checkVar&Sequence_109",
        "ItemDescription&Sequence_110",
        "NewTab&Sequence_111",
        "newTabUrl&Sequence_111",
        "Array2&Sequence_111",
        "Department1&Sequence_111",
        "Department2&Sequence_111",
        "Department5&Sequence_111",
        "Department6&Sequence_111",
        "Department3&Sequence_111",
        "Department4&Sequence_111",
        "Array&Sequence_112",
        "ItemDescription&Sequence_113",
        "Errormsg&Sequence_1"
      ],
      "ArgumentsSectionElementsOrder": [
        "I_DataRow",
        "I_PO",
        "I_SellPrice",
        "I_Route",
        "O_Ver_Result_Bool",
        "O_Output_msg",
        "I_Qty",
        "I_ItemCode",
        "I_Customer",
        "I_OrderType",
        "I_Company",
        "I_Division",
        "IO_Present_URL"
      ],
      "ConstantsSectionElementsOrder": [],
      "AddedNamespaces": null
    },
    {
      "Path": "TC_011.xaml",
      "SortBy": 0,
      "VariablesSectionElementsOrder": [
        "Statusmsg&Sequence_1",
        "Errormsg&Sequence_1",
        "Cycle_value&Sequence_1",
        "Row&Sequence_2"
      ],
      "ArgumentsSectionElementsOrder": [
        "I_Route",
        "I_PO",
        "I_SellPrice",
        "O_Ver_Result_Bool",
        "O_Output_msg",
        "I_Qty",
        "I_ItemCode",
        "I_Customer",
        "I_OrderType",
        "I_Company",
        "I_Division",
        "IO_Present_URL"
      ],
      "ConstantsSectionElementsOrder": [],
      "AddedNamespaces": null
    },
    {
      "Path": "TC_012.xaml",
      "SortBy": 0,
      "VariablesSectionElementsOrder": [
        "OrderScreen&Sequence_1",
        "Errormsg&Sequence_1",
        "ItemDescription&Sequence_2"
      ],
      "ArgumentsSectionElementsOrder": [
        "I_Qty",
        "I_ItemCode",
        "O_Ver_Result_Bool",
        "O_Output_msg",
        "I_PO",
        "I_Route",
        "I_SellPrice",
        "I_Customer",
        "I_OrderType",
        "I_Company",
        "I_Division",
        "IO_Present_URL"
      ],
      "ConstantsSectionElementsOrder": [],
      "AddedNamespaces": null
    },
    {
      "Path": "TC_013.xaml",
      "SortBy": 0,
      "VariablesSectionElementsOrder": [
        "Errormsg&Sequence_1",
        "OrderScreen&Sequence_1",
        "ItemDescription&Sequence_3",
        "ItemDescription&Sequence_2"
      ],
      "ArgumentsSectionElementsOrder": [
        "I_PO",
        "I_Route",
        "I_Qty",
        "I_ItemCode",
        "I_SellPrice",
        "I_Company",
        "O_Output_msg",
        "O_Ver_Result_Bool",
        "I_OrderType",
        "I_Customer",
        "I_Division",
        "IO_Present_URL"
      ],
      "ConstantsSectionElementsOrder": [],
      "AddedNamespaces": null
    },
    {
      "Path": "EmailAuto.xaml",
      "SortBy": 0,
      "VariablesSectionElementsOrder": [
        "Index&Sequence_1",
        "Row_Color&Sequence_1",
        "Execution_color&Sequence_1",
        "Excel_Row_Count&Sequence_1",
        "Data&Sequence_1",
        "CountOfPass&Sequence_1"
      ],
      "ArgumentsSectionElementsOrder": [],
      "ConstantsSectionElementsOrder": [],
      "AddedNamespaces": null
    },
    {
      "Path": "GS008_Validate_Contract_Item_For_StoreItem_Combination_In_Order_Screen.xaml",
      "SortBy": 0,
      "VariablesSectionElementsOrder": [
        "AC_Value&Sequence_1",
        "Qnt_Errormsg&Sequence_2",
        "Errormsg&Sequence_2",
        "SellValue&Sequence_3",
        "ItemDescription&Sequence_4"
      ],
      "ArgumentsSectionElementsOrder": [
        "I_DataRow",
        "IO_Present_URL",
        "O_Output_msg",
        "O_Ver_Result_Bool"
      ],
      "ConstantsSectionElementsOrder": [],
      "AddedNamespaces": null
    },
    {
      "Path": "GS001_Test_Error_For_Invalid_Customer.xaml",
      "SortBy": 0,
      "VariablesSectionElementsOrder": [
        "Errormsg&Sequence_1",
        "OrderScreen&Sequence_1",
        "ItemDescription&Sequence_5"
      ],
      "ArgumentsSectionElementsOrder": [
        "I_DataRow",
        "IO_Present_URL",
        "O_Output_msg",
        "O_Ver_Result_Bool"
      ],
      "ConstantsSectionElementsOrder": [],
      "AddedNamespaces": null
    },
    {
      "Path": "GS004_Test_Error_When_No_SellPrice.xaml",
      "SortBy": 0,
      "VariablesSectionElementsOrder": [
        "Errormsg&Sequence_1",
        "SellValue&Sequence_1",
        "Price_Errormsg&Sequence_1",
        "Array_Error&Sequence_1",
        "ItemDescription&Sequence_2"
      ],
      "ArgumentsSectionElementsOrder": [
        "I_DataRow",
        "IO_Present_URL",
        "O_Output_msg",
        "O_Ver_Result_Bool"
      ],
      "ConstantsSectionElementsOrder": [],
      "AddedNamespaces": null
    },
    {
      "Path": "GS002_Test_Error_For Store_on_CreditHold.xaml",
      "SortBy": 0,
      "VariablesSectionElementsOrder": [
        "Errormsg&Sequence_1",
        "OrderScreen&Sequence_1",
        "Present_URL&Sequence_18",
        "ItemDescription&Sequence_2"
      ],
      "ArgumentsSectionElementsOrder": [
        "I_DataRow",
        "O_Output_msg",
        "O_Ver_Result_Bool",
        "IO_Present_URL"
      ],
      "ConstantsSectionElementsOrder": [],
      "AddedNamespaces": null
    },
    {
      "Path": "GS005_Test_Internal_Toggle_Button.xaml",
      "SortBy": 0,
      "VariablesSectionElementsOrder": [
        "internal_toggle&Sequence_1",
        "Errormsg&Sequence_2"
      ],
      "ArgumentsSectionElementsOrder": [
        "I_DataRow",
        "IO_Present_URL",
        "O_Output_msg",
        "O_Ver_Result_Bool"
      ],
      "ConstantsSectionElementsOrder": [],
      "AddedNamespaces": null
    },
    {
      "Path": "GS003_Test_Error_When_No_Quantity.xaml",
      "SortBy": 0,
      "VariablesSectionElementsOrder": [
        "Qnt_Error_Msg&Sequence_1",
        "Errormsg&Sequence_1",
        "Error_Array&Sequence_1"
      ],
      "ArgumentsSectionElementsOrder": [
        "I_DataRow",
        "IO_Present_URL",
        "O_Output_msg",
        "O_Ver_Result_Bool"
      ],
      "ConstantsSectionElementsOrder": [],
      "AddedNamespaces": null
    },
    {
      "Path": "GS006_Submit_InternalOrder_With_Manual_Route.xaml",
      "SortBy": 0,
      "VariablesSectionElementsOrder": [
        "OrderId&Sequence_1",
        "WMS_check_box&Sequence_1",
        "internal_toggle&Sequence_1",
        "OrderStatus&Sequence_1"
      ],
      "ArgumentsSectionElementsOrder": [
        "I_DataRow",
        "O_Output_msg",
        "O_Ver_Result_Bool",
        "IO_Present_URL"
      ],
      "ConstantsSectionElementsOrder": [],
      "AddedNamespaces": null
    },
    {
      "Path": "GS007_Test_Error_When_No_PoNumber_For_InternalOrder.xaml",
      "SortBy": 0,
      "VariablesSectionElementsOrder": [
        "internal_toggle&Sequence_1",
        "Errormsg&Sequence_1"
      ],
      "ArgumentsSectionElementsOrder": [
        "I_DataRow",
        "O_Output_msg",
        "O_Ver_Result_Bool",
        "IO_Present_URL"
      ],
      "ConstantsSectionElementsOrder": [],
      "AddedNamespaces": null
    },
    {
      "Path": "GS009_Test_Error_When_Price_Override_IsGreaterThan_15Percentage.xaml",
      "SortBy": 0,
      "VariablesSectionElementsOrder": [
        "Sell_D&Sequence_1",
        "SellValue&Sequence_1",
        "Warning&Sequence_1",
        "FoundElement&Sequence_1",
        "Price_Errormsg&Sequence_1",
        "Qnt_Errormsg&Sequence_2",
        "ItemDescription&Sequence_3",
        "ItemDescription&Sequence_4"
      ],
      "ArgumentsSectionElementsOrder": [
        "I_DataRow",
        "IO_Present_URL",
        "O_Output_msg",
        "O_Ver_Result_Bool"
      ],
      "ConstantsSectionElementsOrder": [],
      "AddedNamespaces": null
    },
    {
      "Path": "GS010_Test_Error When_Item_Description_Is_Missing.xaml",
      "SortBy": 0,
      "VariablesSectionElementsOrder": [
        "ItemDesc&Sequence_1",
        "Errormsg&Sequence_1"
      ],
      "ArgumentsSectionElementsOrder": [
        "I_DataRow",
        "IO_Present_URL",
        "O_Output_msg",
        "O_Ver_Result_Bool"
      ],
      "ConstantsSectionElementsOrder": [],
      "AddedNamespaces": null
    },
    {
      "Path": "GS011_Test_Order_Creation_when _No Cycle.xaml",
      "SortBy": 0,
      "VariablesSectionElementsOrder": [
        "Cycle_value&Sequence_1",
        "Errormsg&Sequence_1",
        "Statusmsg&Sequence_1",
        "Row&Sequence_2"
      ],
      "ArgumentsSectionElementsOrder": [
        "I_DataRow",
        "IO_Present_URL",
        "O_Output_msg",
        "O_Ver_Result_Bool"
      ],
      "ConstantsSectionElementsOrder": [],
      "AddedNamespaces": null
    },
    {
      "Path": "GS012_Test_Error_When GS_PrimaryShipFlag_Is_N.xaml",
      "SortBy": 0,
      "VariablesSectionElementsOrder": [
        "Errormsg&Sequence_1",
        "OrderScreen&Sequence_1",
        "ItemDescription&Sequence_2"
      ],
      "ArgumentsSectionElementsOrder": [
        "I_DataRow",
        "IO_Present_URL",
        "O_Output_msg",
        "O_Ver_Result_Bool"
      ],
      "ConstantsSectionElementsOrder": [],
      "AddedNamespaces": null
    },
    {
      "Path": "GS013_Test_Error_When_NoBilling_Schedule.xaml",
      "SortBy": 0,
      "VariablesSectionElementsOrder": [
        "OrderScreen&Sequence_1",
        "Errormsg&Sequence_1",
        "ItemDescription&Sequence_3",
        "ItemDescription&Sequence_2"
      ],
      "ArgumentsSectionElementsOrder": [
        "I_DataRow",
        "IO_Present_URL",
        "O_Ver_Result_Bool",
        "O_Output_msg"
      ],
      "ConstantsSectionElementsOrder": [],
      "AddedNamespaces": null
    },
    {
      "Path": "TC_018.xaml",
      "SortBy": 0,
      "VariablesSectionElementsOrder": [
        "Data&Sequence_34",
        "Item_IsAlphaNumeric&Sequence_1",
        "ItemDescp&Sequence_1",
        "Alpha_num_Error_Msg&Sequence_1",
        "Itemcode_array&Sequence_1"
      ],
      "ArgumentsSectionElementsOrder": [
        "O_Ver_Result_Bool",
        "O_Output_msg",
        "I_DataRow",
        "IO_Present_URL"
      ],
      "ConstantsSectionElementsOrder": [],
      "AddedNamespaces": null
    },
    {
      "Path": "TC_019_Test_Item_Related_Info_Populated.xaml",
      "SortBy": 0,
      "VariablesSectionElementsOrder": [
        "Alpha_num_Error_Msg&Sequence_1",
        "DataTable&Sequence_1",
        "Output_DT&Sequence_1",
        "ItemDescp&Sequence_1",
        "Item_IsAlphaNumeric&Sequence_1",
        "Itemcode_array&Sequence_1"
      ],
      "ArgumentsSectionElementsOrder": [
        "O_Ver_Result_Bool",
        "I_DataRow",
        "IO_Present_URL",
        "O_Output_msg"
      ],
      "ConstantsSectionElementsOrder": [],
      "AddedNamespaces": null
    },
    {
      "Path": "TC_069.xaml",
      "SortBy": 0,
      "VariablesSectionElementsOrder": [
        "DataTable&Sequence_1",
        "Current_DT_Row&Sequence_1",
        "Output_DT&Sequence_1",
        "DT_Row_Count&Sequence_1",
        "Count_Items&Sequence_1"
      ],
      "ArgumentsSectionElementsOrder": [
        "IO_Present_URL",
        "I_DataRow",
        "O_Output_msg",
        "O_Ver_Result_Bool"
      ],
      "ConstantsSectionElementsOrder": [],
      "AddedNamespaces": null
    },
    {
      "Path": "GS018_Test_Item_code_digits_alpha_numeric.xaml",
      "SortBy": 0,
      "VariablesSectionElementsOrder": [
        "Itemcode_array&Sequence_1",
        "Alpha_num_Error_Msg&Sequence_1",
        "ItemDescp&Sequence_1",
        "Item_IsAlphaNumeric&Sequence_1",
        "Data&Sequence_34"
      ],
      "ArgumentsSectionElementsOrder": [
        "IO_Present_URL",
        "I_DataRow",
        "O_Output_msg",
        "O_Ver_Result_Bool"
      ],
      "ConstantsSectionElementsOrder": [],
      "AddedNamespaces": null
    },
    {
      "Path": "TC_020_Ease_Of_Entering_Item.xaml",
      "SortBy": 0,
      "VariablesSectionElementsOrder": [
        "DataTable&Sequence_1",
        "Output_DT&Sequence_1",
        "ItemCode_Array&Sequence_1"
      ],
      "ArgumentsSectionElementsOrder": [
        "IO_Present_URL",
        "I_DataRow",
        "O_Output_msg",
        "O_Ver_Result_Bool"
      ],
      "ConstantsSectionElementsOrder": [],
      "AddedNamespaces": null
    },
    {
      "Path": "TC_021_Validate_Qty_Field_For_Numeric_AlphaNumeric.xaml",
      "SortBy": 0,
      "VariablesSectionElementsOrder": [
        "Quantity_array&Sequence_1",
        "Qty_IsAlphaNumeric&Sequence_1",
        "ItemDescp&Sequence_1",
        "Alpha_num_Error_Msg&Sequence_1",
        "Error_Array&Sequence_1",
        "Errormsg&Sequence_1"
      ],
      "ArgumentsSectionElementsOrder": [
        "IO_Present_URL",
        "I_DataRow",
        "O_Output_msg",
        "O_Ver_Result_Bool"
      ],
      "ConstantsSectionElementsOrder": [],
      "AddedNamespaces": null
    },
    {
      "Path": "TC_024_Test_PO_Number_Max_Length.xaml",
      "SortBy": 0,
      "VariablesSectionElementsOrder": [
        "OrderScreen&Sequence_1",
        "Errormsg&Sequence_1",
        "ItemDescription&Sequence_32",
        "ItemDescription&Sequence_35"
      ],
      "ArgumentsSectionElementsOrder": [
        "IO_Present_URL",
        "I_Division",
        "I_Customer",
        "I_OrderType",
        "O_Ver_Result_Bool",
        "O_Output_msg",
        "I_Company",
        "I_SellPrice",
        "I_ItemCode",
        "I_Qty",
        "I_Route",
        "I_PO",
        "I_DataRow"
      ],
      "ConstantsSectionElementsOrder": [],
      "AddedNamespaces": null
    },
    {
      "Path": "TC_034_Test_Quantity_Tolerance.xaml",
      "SortBy": 0,
      "VariablesSectionElementsOrder": [
        "QtyTolerance&Sequence_1",
        "ErrorMsg&Sequence_3"
      ],
      "ArgumentsSectionElementsOrder": [
        "I_DataRow",
        "IO_Present_URL",
        "O_Output_msg",
        "O_Ver_Result_Bool"
      ],
      "ConstantsSectionElementsOrder": [],
      "AddedNamespaces": null
    },
    {
      "Path": "TC_042_Test_Duplicate_Order.xaml",
      "SortBy": 0,
      "VariablesSectionElementsOrder": [
        "ErrorMsg&Sequence_1",
        "Order_Submit&Sequence_1"
      ],
      "ArgumentsSectionElementsOrder": [
        "IO_Present_URL",
        "I_DataRow",
        "O_Output_msg",
        "O_Ver_Result_Bool"
      ],
      "ConstantsSectionElementsOrder": [],
      "AddedNamespaces": null
    },
    {
      "Path": "LoginTestCase.xaml",
      "SortBy": 0,
      "VariablesSectionElementsOrder": [
        "Errormsg&Sequence_1",
        "LoginText&Sequence_1",
        "SwitchMode&Sequence_1",
        "Switch&Sequence_1",
        "UserName&Sequence_1",
        "PassWord&Sequence_1"
      ],
      "ArgumentsSectionElementsOrder": [
        "IO_present_URL",
        "I_UserName",
        "I_PassWord",
        "I_URL",
        "O_Output_msg",
        "O_Ver_Result_Bool"
      ],
      "ConstantsSectionElementsOrder": [],
      "AddedNamespaces": null
    },
    {
      "Path": "Framework.xaml",
      "SortBy": 0,
      "VariablesSectionElementsOrder": [
        "strRootDirectory&Sequence_2",
        "ConfigFile&Sequence_1",
        "ConfigSheet&Sequence_1",
        "TestDataFile&Sequence_1",
        "TestDataSheet&Sequence_1",
        "configDT&Sequence_1",
        "Out_Config&Sequence_1",
        "Testdata_DT&Sequence_1",
        "EnvUrlName&Sequence_1",
        "URL&Sequence_1",
        "UserName&Sequence_1",
        "PassWord&Sequence_1",
        "present_url&Sequence_1",
        "Exception&Sequence_1",
        "Output_msg&Sequence_1",
        "Ver_Result_Bool&Sequence_1",
        "Start_Time&Sequence_1",
        "DataRow&Sequence_1",
        "end_time&Sequence_1",
        "Seconds&Sequence_19"
      ],
      "ArgumentsSectionElementsOrder": [],
      "ConstantsSectionElementsOrder": [],
      "AddedNamespaces": null
    },
    {
      "Path": "TC_036_Test_Header_Notes.xaml",
      "SortBy": 0,
      "VariablesSectionElementsOrder": [
        "Written_Notes&Sequence_1",
        "Verify_Written_Notes&Sequence_1"
      ],
      "ArgumentsSectionElementsOrder": [
        "IO_Present_URL",
        "I_DataRow",
        "O_Ver_Result_Bool",
        "O_Output_msg"
      ],
      "ConstantsSectionElementsOrder": [],
      "AddedNamespaces": null
    },
    {
      "Path": "TC_025_Test_Price_Override_Under_Limit_With_Yellow_Sign.xaml",
      "SortBy": 0,
      "VariablesSectionElementsOrder": [
        "Sell_D&Sequence_1",
        "SellValue&Sequence_1",
        "FoundElement&Sequence_1",
        "Warning&Sequence_1",
        "Sell_D2&Sequence_1",
        "YellowSymbol&Sequence_1",
        "sellSymbol&Sequence_1",
        "Symbol&Sequence_5",
        "Qnt_Errormsg&Sequence_2",
        "ItemDescription&Sequence_3",
        "ItemDescription&Sequence_4"
      ],
      "ArgumentsSectionElementsOrder": [
        "IO_Present_URL",
        "I_DataRow",
        "O_Output_msg",
        "O_Ver_Result_Bool"
      ],
      "ConstantsSectionElementsOrder": [],
      "AddedNamespaces": null
    },
    {
      "Path": "TC_026_Validate_Substitution_Available_Symbol.xaml",
      "SortBy": 0,
      "VariablesSectionElementsOrder": [
        "substitute_Item_symbol&Sequence_1",
        "BlueBallon&Sequence_1",
        "Symbol&Sequence_1",
        "Warning&Sequence_1",
        "Icon&Sequence_1",
        "Sub_Item&Sequence_1",
        "Qnt_Errormsg&Sequence_3",
        "ItemDescription&Sequence_4",
        "ItemDescription&Sequence_5"
      ],
      "ArgumentsSectionElementsOrder": [
        "IO_Present_URL",
        "I_DataRow",
        "O_Output_msg",
        "O_Ver_Result_Bool"
      ],
      "ConstantsSectionElementsOrder": [],
      "AddedNamespaces": null
    },
    {
      "Path": "TC_033_Test_DeliveryType_Functionality.xaml",
      "SortBy": 0,
      "VariablesSectionElementsOrder": [
        "CheckDashCode2&Sequence_1",
        "DeliveryType&Sequence_1",
        "ChangedDeliveryType&Sequence_1",
        "ValueFromDropDown&Sequence_2",
        "ValueFromDropDown2&Sequence_2"
      ],
      "ArgumentsSectionElementsOrder": [
        "IO_Present_URL",
        "I_DataRow",
        "O_Output_msg",
        "O_Ver_Result_Bool"
      ],
      "ConstantsSectionElementsOrder": [],
      "AddedNamespaces": null
    },
    {
      "Path": "TC_037_Save_Order.xaml",
      "SortBy": 0,
      "VariablesSectionElementsOrder": [
        "FetchOrderDetails&Sequence_5",
        "OrderDescription&Sequence_5"
      ],
      "ArgumentsSectionElementsOrder": [
        "I_DataRow",
        "IO_Present_URL",
        "O_Output_msg",
        "O_Ver_Result_Bool"
      ],
      "ConstantsSectionElementsOrder": [],
      "AddedNamespaces": null
    },
    {
      "Path": "TC_038_Skip_Item_Order_Limit.xaml",
      "SortBy": 0,
      "VariablesSectionElementsOrder": [
        "ErrorMsg&Sequence_2",
        "QtyTolerance&Sequence_2"
      ],
      "ArgumentsSectionElementsOrder": [
        "IO_Present_URL",
        "I_DataRow",
        "O_Output_msg",
        "O_Ver_Result_Bool"
      ],
      "ConstantsSectionElementsOrder": [],
      "AddedNamespaces": null
    },
    {
      "Path": "TC_039_Test_Seasonal_Item.xaml",
      "SortBy": 0,
      "VariablesSectionElementsOrder": [
        "SessionalItem&Sequence_15"
      ],
      "ArgumentsSectionElementsOrder": [
        "IO_Present_URL",
        "I_DataRow",
        "O_Output_msg",
        "O_Ver_Result_Bool"
      ],
      "ConstantsSectionElementsOrder": [],
      "AddedNamespaces": null
    },
    {
      "Path": "TC_041_Identifying_Item_Type_A_R_C.xaml",
      "SortBy": 0,
      "VariablesSectionElementsOrder": [
        "ACR_Value&Sequence_1",
        "text&Sequence_1",
        "Qnt_Errormsg&Sequence_2",
        "Errormsg&Sequence_2"
      ],
      "ArgumentsSectionElementsOrder": [
        "IO_Present_URL",
        "O_Output_msg",
        "O_Ver_Result_Bool",
        "I_DataRow"
      ],
      "ConstantsSectionElementsOrder": [],
      "AddedNamespaces": null
    },
    {
      "Path": "TC_045_Test_Invalid_and_InactiveCodes_Code_With_No_Info_Populated.xaml",
      "SortBy": 0,
      "VariablesSectionElementsOrder": [
        "OrderScreen&Sequence_1",
        "Errormsg&Sequence_1"
      ],
      "ArgumentsSectionElementsOrder": [
        "IO_Present_URL",
        "I_Division",
        "I_Customer",
        "I_OrderType",
        "O_Ver_Result_Bool",
        "O_Output_msg",
        "I_Company",
        "I_SellPrice",
        "I_ItemCode",
        "I_Qty",
        "I_Route",
        "I_PO",
        "I_DataRow"
      ],
      "ConstantsSectionElementsOrder": [],
      "AddedNamespaces": null
    },
    {
      "Path": "TC_031_Test_IgnoreLead_Button_For_User.xaml",
      "SortBy": 0,
      "VariablesSectionElementsOrder": [
        "ButtonState&Sequence_1",
        "ButtonColor&Sequence_19"
      ],
      "ArgumentsSectionElementsOrder": [
        "IO_Present_URL",
        "I_DataRow",
        "O_Output_msg",
        "O_Ver_Result_Bool"
      ],
      "ConstantsSectionElementsOrder": [],
      "AddedNamespaces": null
    },
    {
      "Path": "TC_032_Test_Min_Override_button.xaml",
      "SortBy": 0,
      "VariablesSectionElementsOrder": [
        "ButtonColor&Sequence_1",
        "ButtonState&Sequence_1"
      ],
      "ArgumentsSectionElementsOrder": [
        "IO_Present_URL",
        "I_DataRow",
        "O_Output_msg",
        "O_Ver_Result_Bool"
      ],
      "ConstantsSectionElementsOrder": [],
      "AddedNamespaces": null
    },
    {
      "Path": "TC_046_Test_Copy_Paste_10_Items.xaml",
      "SortBy": 0,
      "VariablesSectionElementsOrder": [
        "DataTable&Sequence_1",
        "Counter_Var&Sequence_1",
        "ListAppeared&Sequence_1",
        "outdt&Sequence_1",
        "List&Sequence_1",
        "Output&Sequence_1",
        "List_of_Items&Sequence_1",
        "outdt&Sequence_2",
        "ExcelDT&Sequence_2",
        "ExcelDT&Sequence_25",
        "CopyData&Sequence_19",
        "Range&Sequence_19",
        "ExcelValue&Sequence_19",
        "Var1&Sequence_19",
        "Items&Sequence_73",
        "group&Sequence_73"
      ],
      "ArgumentsSectionElementsOrder": [
        "IO_Present_URL",
        "I_DataRow",
        "O_Ver_Result_Bool",
        "O_Output_msg"
      ],
      "ConstantsSectionElementsOrder": [],
      "AddedNamespaces": null
    },
    {
      "Path": "TC_052_Test_Match_DeliverTo.xaml",
      "SortBy": 0,
      "VariablesSectionElementsOrder": [
        "store_search_count&Sequence_56",
        "Stores&Sequence_56",
        "I_Customer&Sequence_5",
        "OrderScreen&Sequence_5",
        "MatchingPatternsResult&Sequence_5",
        "Text&Sequence_5",
        "Text2&Sequence_5",
        "MatchingPatternsResult2&Sequence_5",
        "ExtractDataTable&Sequence_5",
        "outdt&Sequence_5",
        "array_of_stores&Sequence_52",
        "ItemDescription&Sequence_6"
      ],
      "ArgumentsSectionElementsOrder": [
        "I_DataRow",
        "O_Output_msg",
        "O_Ver_Result_Bool",
        "IO_Present_URL"
      ],
      "ConstantsSectionElementsOrder": [],
      "AddedNamespaces": null
    },
    {
      "Path": "TC_057_Test_Item_Second_Line_Same_Item_Duplicate.xaml",
      "SortBy": 0,
      "VariablesSectionElementsOrder": [
        "Error_msg&Sequence_5",
        "ExtractDataTable&Sequence_6",
        "Ad_Item_Toggle_Screen&Sequence_6",
        "Items&Sequence_7",
        "group&Sequence_7",
        "I_Customer&Sequence_5",
        "OrderScreen&Sequence_5",
        "MatchingPatternsResult&Sequence_5",
        "Text&Sequence_5",
        "Text2&Sequence_5",
        "MatchingPatternsResult2&Sequence_5",
        "ExtractDataTable&Sequence_5",
        "outdt&Sequence_5",
        "Company&Sequence_5",
        "ItemDescription&Sequence_8"
      ],
      "ArgumentsSectionElementsOrder": [
        "O_Output_msg",
        "O_Ver_Result_Bool",
        "I_DataRow",
        "IO_Present_URL"
      ],
      "ConstantsSectionElementsOrder": [],
      "AddedNamespaces": null
    },
    {
      "Path": "TC_059_Test_Clicking_Delete_No.xaml",
      "SortBy": 0,
      "VariablesSectionElementsOrder": [
        "I_Customer&Sequence_5",
        "OrderScreen&Sequence_5",
        "MatchingPatternsResult&Sequence_5",
        "Text&Sequence_5",
        "Text2&Sequence_5",
        "MatchingPatternsResult2&Sequence_5",
        "ExtractDataTable&Sequence_5",
        "outdt&Sequence_5",
        "Company&Sequence_5",
        "ItemDescription&Sequence_8"
      ],
      "ArgumentsSectionElementsOrder": [
        "IO_Present_URL",
        "O_Output_msg",
        "O_Ver_Result_Bool",
        "I_DataRow"
      ],
      "ConstantsSectionElementsOrder": [],
      "AddedNamespaces": null
    },
    {
      "Path": "TC_060_Test_Clicking_Delete_Yes.xaml",
      "SortBy": 0,
      "VariablesSectionElementsOrder": [
        "I_Customer&Sequence_5",
        "OrderScreen&Sequence_5",
        "MatchingPatternsResult&Sequence_5",
        "Text&Sequence_5",
        "Text2&Sequence_5",
        "MatchingPatternsResult2&Sequence_5",
        "ExtractDataTable&Sequence_5",
        "outdt&Sequence_5",
        "Company&Sequence_5",
        "ItemDescription&Sequence_8"
      ],
      "ArgumentsSectionElementsOrder": [
        "IO_Present_URL",
        "O_Output_msg",
        "O_Ver_Result_Bool",
        "I_DataRow"
      ],
      "ConstantsSectionElementsOrder": [],
      "AddedNamespaces": null
    },
    {
      "Path": "TC_061_Test_AD_Item_Toggle.xaml",
      "SortBy": 0,
      "VariablesSectionElementsOrder": [
        "outDT&Sequence_7",
        "store_search_count&Sequence_45",
        "DisplayName&Sequence_45",
        "OrderScreen&Sequence_6",
        "ExtractDataTable&Sequence_7",
        "Ad_Item_Toggle_Screen&Sequence_7",
        "Text&Sequence_7",
        "Stores&Sequence_53",
        "array_of_stores&Sequence_53",
        "Types&Sequence_53",
        "array_of_types&Sequence_53",
        "ItemDescription&Sequence_5"
      ],
      "ArgumentsSectionElementsOrder": [
        "IO_Present_URL",
        "O_Output_msg",
        "O_Ver_Result_Bool",
        "I_DataRow"
      ],
      "ConstantsSectionElementsOrder": [],
      "AddedNamespaces": null
    },
    {
      "Path": "TC_056_Test_Item_Search_Duplicate.xaml",
      "SortBy": 0,
      "VariablesSectionElementsOrder": [
        "store_search_count&",
        "DisplayName&",
        "OrderScreen&",
        "ExtractDataTable&",
        "Ad_Item_Toggle_Screen&",
        "Text&",
        "Stores&",
        "array_of_stores&",
        "Types&",
        "array_of_types&",
        "ItemDescription&"
      ],
      "ArgumentsSectionElementsOrder": [
        "IO_Present_URL",
        "O_Output_msg",
        "O_Ver_Result_Bool",
        "I_DataRow"
      ],
      "ConstantsSectionElementsOrder": [],
      "AddedNamespaces": null
    },
    {
      "Path": "TC_062_Test_Item_Related_To_Company_Search.xaml",
      "SortBy": 0,
      "VariablesSectionElementsOrder": [
        "List_of_Items&Sequence_59",
        "Item_search_count&Sequence_59",
        "I_Customer&Sequence_5",
        "OrderScreen&Sequence_5",
        "MatchingPatternsResult&Sequence_5",
        "Text&Sequence_5",
        "Text2&Sequence_5",
        "MatchingPatternsResult2&Sequence_5",
        "ExtractDataTable&Sequence_5",
        "outdt&Sequence_5",
        "Company&Sequence_5",
        "ExtractDataTable&Sequence_6",
        "Ad_Item_Toggle_Screen&Sequence_6",
        "Items&Sequence_7",
        "group&Sequence_7",
        "ItemDescription&Sequence_8"
      ],
      "ArgumentsSectionElementsOrder": [
        "IO_Present_URL",
        "O_Output_msg",
        "O_Ver_Result_Bool",
        "I_DataRow"
      ],
      "ConstantsSectionElementsOrder": [],
      "AddedNamespaces": null
    },
    {
      "Path": "TC_064_Item_Search_Frame_Filter.xaml",
      "SortBy": 0,
      "VariablesSectionElementsOrder": [
        "ShowBlanks&Sequence_1",
        "result1&Sequence_1",
        "result2&Sequence_1",
        "result3&Sequence_1",
        "ShowNoBlanks&Sequence_1",
        "FilterItem&Sequence_1",
        "ErrorMsg&Sequence_2",
        "QtyTolerance&Sequence_2",
        "opt1&Sequence_4",
        "opt2&Sequence_4",
        "opt3&Sequence_4"
      ],
      "ArgumentsSectionElementsOrder": [
        "IO_Present_URL",
        "I_DataRow",
        "O_Output_msg",
        "O_Ver_Result_Bool"
      ],
      "ConstantsSectionElementsOrder": [],
      "AddedNamespaces": null
    },
    {
      "Path": "TC_065_Switching_Toggle_Should_Show_AdPrice.xaml",
      "SortBy": 0,
      "VariablesSectionElementsOrder": [
        "OrderScreen&Sequence_1",
        "Output&Sequence_1",
        "ConfirmItem&Sequence_1",
        "Errormsg&Sequence_1",
        "ListAppeared&Sequence_1",
        "Counter_Var&Sequence_1",
        "ExtractDataTable&Sequence_1",
        "outdt&Sequence_6",
        "ItemInDt&Sequence_28"
      ],
      "ArgumentsSectionElementsOrder": [
        "IO_Present_URL",
        "O_Output_msg",
        "O_Ver_Result_Bool",
        "I_DataRow"
      ],
      "ConstantsSectionElementsOrder": [],
      "AddedNamespaces": null
    },
    {
      "Path": "TC_035_Test_Cycle_For_Entry_UI.xaml",
      "SortBy": 0,
      "VariablesSectionElementsOrder": [
        "ValueFromDropDown&Sequence_2",
        "ValueFromDropDown2&Sequence_2",
        "Cycle&Sequence_2"
      ],
      "ArgumentsSectionElementsOrder": [
        "IO_Present_URL",
        "I_DataRow",
        "O_Output_msg",
        "O_Ver_Result_Bool"
      ],
      "ConstantsSectionElementsOrder": [],
      "AddedNamespaces": null
    },
    {
      "Path": "TC_058_Test_New_Icon_On_Existing_Page.xaml",
      "SortBy": 0,
      "VariablesSectionElementsOrder": [
        "Error_msg&Sequence_66",
        "I_Customer&Sequence_5",
        "OrderScreen&Sequence_5",
        "Text&Sequence_5",
        "Text2&Sequence_5",
        "ExtractDataTable&Sequence_5",
        "ItemDescription&Sequence_8"
      ],
      "ArgumentsSectionElementsOrder": [
        "IO_Present_URL",
        "O_Output_msg",
        "O_Ver_Result_Bool",
        "I_DataRow"
      ],
      "ConstantsSectionElementsOrder": [],
      "AddedNamespaces": null
    },
    {
      "Path": "TC_044_Select_Retailers_BasedOn_Number_Phone_City.xaml",
      "SortBy": 0,
      "VariablesSectionElementsOrder": [
        "OrderScreen&Sequence_1",
        "Errormsg&Sequence_1",
        "Output&Sequence_1",
        "List_of_Items&Sequence_1",
        "Item_search_count&Sequence_1",
        "TableData&Sequence_1",
        "Counter_Var&Sequence_1",
        "outdt&Sequence_1",
        "ListAppeared&Sequence_1",
        "Appeared_Value&Sequence_47",
        "Appeared_Value&Sequence_48",
        "Appeared_Value&Sequence_49",
        "Appeared_Value&Sequence_50",
        "ItemDescription&Sequence_3"
      ],
      "ArgumentsSectionElementsOrder": [
        "IO_Present_URL",
        "I_Division",
        "I_Customer",
        "I_OrderType",
        "O_Ver_Result_Bool",
        "I_SellPrice",
        "I_ItemCode",
        "I_Company",
        "I_Qty",
        "I_Route",
        "I_PO",
        "O_Output_msg",
        "I_DataRow"
      ],
      "ConstantsSectionElementsOrder": [],
      "AddedNamespaces": null
    },
    {
      "Path": "TC_070_Check_Item_Details_Info_At_The_Bottom_Of_Screen.xaml",
      "SortBy": 0,
      "VariablesSectionElementsOrder": [
        "Qty&Sequence_1",
        "SellTotal&Sequence_1",
        "ItemCodeCount&Sequence_1",
        "variable1&Sequence_35",
        "QtyCount&Sequence_1",
        "outdt&Sequence_18",
        "str&Sequence_1",
        "Table&Sequence_18",
        "DataTable&Sequence_1",
        "Counter_Var&Sequence_1",
        "ListAppeared&Sequence_1",
        "OrderDescription&Sequence_2",
        "FetchOrderDetails&Sequence_2"
      ],
      "ArgumentsSectionElementsOrder": [
        "O_Ver_Result_Bool",
        "O_Output_msg",
        "I_DataRow",
        "IO_Present_URL"
      ],
      "ConstantsSectionElementsOrder": [],
      "AddedNamespaces": null
    },
    {
      "Path": "TC_023_Test_ItemSearch_User_Can_Choose_Single_Item.xaml",
      "SortBy": 0,
      "VariablesSectionElementsOrder": [
        "OrderScreen&Sequence_1",
        "Errormsg&Sequence_1",
        "Output&Sequence_1",
        "ConfirmItem&Sequence_1"
      ],
      "ArgumentsSectionElementsOrder": [
        "IO_Present_URL",
        "I_Division",
        "I_Customer",
        "I_OrderType",
        "O_Ver_Result_Bool",
        "O_Output_msg",
        "I_Company",
        "I_SellPrice",
        "I_ItemCode",
        "I_Qty",
        "I_Route",
        "I_PO",
        "I_DataRow"
      ],
      "ConstantsSectionElementsOrder": [],
      "AddedNamespaces": null
    },
    {
      "Path": "TC_071.xaml",
      "SortBy": 0,
      "VariablesSectionElementsOrder": [
        "SetAttribute&Sequence_39",
        "texxt&Sequence_39",
        "value&Sequence_1",
        "FetchOrderDetails&Sequence_1",
        "OrderDescription&Sequence_1",
        "NewTabUrl&Sequence_1",
        "ItemDetailsOnNewTab&Sequence_1",
        "ItemSubItemSub&Sequence_23",
        "ItemSub&Sequence_23",
        "ItemDetails&Sequence_25",
        "ItemDetails&Sequence_1",
        "ItemDetailsSubstitution&Sequence_1"
      ],
      "ArgumentsSectionElementsOrder": [
        "O_Ver_Result_Bool",
        "O_Output_msg",
        "I_DataRow",
        "IO_Present_URL"
      ],
      "ConstantsSectionElementsOrder": [],
      "AddedNamespaces": null
    },
    {
      "Path": "TC_073.xaml",
      "SortBy": 0,
      "VariablesSectionElementsOrder": [
        "ErrorMsg&Sequence_2",
        "QtyTolerance&Sequence_2",
        "opt1&Sequence_3",
        "opt2&Sequence_3",
        "opt3&Sequence_3"
      ],
      "ArgumentsSectionElementsOrder": [
        "O_Ver_Result_Bool",
        "O_Output_msg",
        "I_DataRow",
        "IO_Present_URL"
      ],
      "ConstantsSectionElementsOrder": [],
      "AddedNamespaces": null
    },
    {
      "Path": "TC_074_Save_Copy_Order_Order_Search.xaml",
      "SortBy": 0,
      "VariablesSectionElementsOrder": [
        "OrderConfirm&Sequence_2",
        "OrderDescription&Sequence_2",
        "FetchOrderDetails&Sequence_2"
      ],
      "ArgumentsSectionElementsOrder": [
        "O_Ver_Result_Bool",
        "O_Output_msg",
        "I_DataRow",
        "IO_Present_URL"
      ],
      "ConstantsSectionElementsOrder": [],
      "AddedNamespaces": null
    },
    {
      "Path": "TC_079.xaml",
      "SortBy": 0,
      "VariablesSectionElementsOrder": [
        "DataTable&Sequence_1",
        "Current_DT_Row&Sequence_1",
        "Output_DT&Sequence_1",
        "DT_Row_Count&Sequence_1",
        "Count_Items&Sequence_1"
      ],
      "ArgumentsSectionElementsOrder": [
        "IO_Present_URL",
        "I_DataRow",
        "O_Output_msg",
        "O_Ver_Result_Bool"
      ],
      "ConstantsSectionElementsOrder": [],
      "AddedNamespaces": null
    },
    {
      "Path": "TC_055_Test_Item_Description_Field_Search_filter.xaml",
      "SortBy": 0,
      "VariablesSectionElementsOrder": [
        "Item_search_count&Sequence_9",
        "List_of_Items&Sequence_9",
        "I_Customer&Sequence_5",
        "OrderScreen&Sequence_5",
        "MatchingPatternsResult&Sequence_5",
        "Text&Sequence_5",
        "Text2&Sequence_5",
        "MatchingPatternsResult2&Sequence_5",
        "ExtractDataTable&Sequence_5",
        "outdt&Sequence_5",
        "ExtractDataTable&Sequence_6",
        "Ad_Item_Toggle_Screen&Sequence_6",
        "Items&Sequence_7",
        "group&Sequence_7",
        "ItemDescription&Sequence_8"
      ],
      "ArgumentsSectionElementsOrder": [
        "IO_Present_URL",
        "I_DataRow",
        "O_Output_msg",
        "O_Ver_Result_Bool"
      ],
      "ConstantsSectionElementsOrder": [],
      "AddedNamespaces": null
    },
    {
      "Path": "TC_075_Check_Home_And_Log_Out_Button.xaml",
      "SortBy": 0,
      "VariablesSectionElementsOrder": [
        "OrderDescription&Sequence_2",
        "FetchOrderDetails&Sequence_2",
        "OrderConfirm&Sequence_2"
      ],
      "ArgumentsSectionElementsOrder": [
        "O_Ver_Result_Bool",
        "O_Output_msg",
        "I_DataRow",
        "IO_Present_URL"
      ],
      "ConstantsSectionElementsOrder": [],
      "AddedNamespaces": null
    },
    {
      "Path": "TC_076_Switching_Screen_from_RegularOder_to_Rush_vice_versa.xaml",
      "SortBy": 0,
      "VariablesSectionElementsOrder": [
        "ErrorMsg&Sequence_2",
        "QtyTolerance&Sequence_2"
      ],
      "ArgumentsSectionElementsOrder": [
        "O_Ver_Result_Bool",
        "O_Output_msg",
        "I_DataRow",
        "IO_Present_URL"
      ],
      "ConstantsSectionElementsOrder": [],
      "AddedNamespaces": null
    },
    {
      "Path": "GS_OP_04_Skip_Item_Substitution.xaml",
      "SortBy": 0,
      "VariablesSectionElementsOrder": [
        "Counter&Sequence_127",
        "getText&Sequence_1",
        "I_Customer&Sequence_2",
        "OrderScreen&Sequence_2",
        "MatchingPatternsResult&Sequence_2",
        "Text&Sequence_2",
        "Text2&Sequence_2",
        "MatchingPatternsResult2&Sequence_2",
        "ExtractDataTable&Sequence_2",
        "outdt&Sequence_2",
        "Company&Sequence_2",
        "Status&Sequence_2",
        "ConfirmationId&Sequence_2",
        "Confirmationmsg&Sequence_2",
        "Sub_Avail&Sequence_17",
        "Skip_Item_Sub&Sequence_66",
        "Counter&Sequence_74",
        "table&Sequence_77",
        "Store&Sequence_77",
        "ItemCode&Sequence_77",
        "BillingDate&Sequence_77",
        "msg&Sequence_78"
      ],
      "ArgumentsSectionElementsOrder": [
        "IO_Present_URL",
        "I_DataRow",
        "O_Output_msg",
        "O_Ver_Result_Bool"
      ],
      "ConstantsSectionElementsOrder": [],
      "AddedNamespaces": null
    },
    {
      "Path": "GS_OP_03_UnauthorizedItem.xaml",
      "SortBy": 0,
      "VariablesSectionElementsOrder": [
        "SellValue&Sequence_134",
        "Counter&Sequence_1",
        "Confirmationmsg&Sequence_1",
        "ConfirmationId&Sequence_1",
        "Status&Sequence_1",
        "ApprovalTypeStatus&Sequence_1",
        "getText&Sequence_1",
        "OrderNumber&Sequence_1",
        "UnauthorizedItem&Sequence_33",
        "Counter&Sequence_74",
        "table&Sequence_121",
        "Store&Sequence_121",
        "ItemCode&Sequence_121",
        "BillingDate&Sequence_121",
        "OrderNumber&Sequence_121"
      ],
      "ArgumentsSectionElementsOrder": [
        "I_DataRow",
        "O_Output_msg",
        "O_Ver_Result_Bool",
        "IO_Present_URL"
      ],
      "ConstantsSectionElementsOrder": [],
      "AddedNamespaces": null
    },
    {
      "Path": "GS_OP_02_No_Billing_Schedule.xaml",
      "SortBy": 0,
      "VariablesSectionElementsOrder": [
        "Counter&Sequence_136",
        "ItemDescription&Sequence_5",
        "NoBillingMsg&Sequence_2",
        "getText&Sequence_1",
        "I_Customer&Sequence_2",
        "OrderScreen&Sequence_2",
        "MatchingPatternsResult&Sequence_2",
        "Text&Sequence_2",
        "Text2&Sequence_2",
        "MatchingPatternsResult2&Sequence_2",
        "ExtractDataTable&Sequence_2",
        "outdt&Sequence_2",
        "Company&Sequence_2",
        "Status&Sequence_2",
        "ConfirmationId&Sequence_2",
        "Confirmationmsg&Sequence_2",
        "Sub_Avail&Sequence_17",
        "Skip_Item_Sub&Sequence_66",
        "Counter&Sequence_74",
        "table&Sequence_77",
        "Store&Sequence_77",
        "ItemCode&Sequence_77",
        "BillingDate&Sequence_77",
        "msg&Sequence_78"
      ],
      "ArgumentsSectionElementsOrder": [
        "IO_Present_URL",
        "I_DataRow",
        "O_Output_msg",
        "O_Ver_Result_Bool"
      ],
      "ConstantsSectionElementsOrder": [],
      "AddedNamespaces": null
    },
    {
      "Path": "GS_OP_006_Sub item_Line level_Rather_than_Original Item.xaml",
      "SortBy": 0,
      "VariablesSectionElementsOrder": [
        "Counter&Sequence_74",
        "BillingDate&Sequence_1",
        "confirmation_id&Sequence_1",
        "getText&Sequence_1",
        "Sub_Item1&Sequence_1",
        "ItemCode&Sequence_5",
        "Datatable&Sequence_5",
        "table&Sequence_5",
        "SellValue&Sequence_5",
        "Sell_D&Sequence_5",
        "FoundElement&Sequence_5",
        "Warning&Sequence_5",
        "text&Sequence_5",
        "Status&Sequence_5",
        "SubItem&Sequence_5",
        "Sub_Item&Sequence_5",
        "Sell_D&Sequence_6",
        "text&Sequence_6",
        "OrderStatus&Sequence_6",
        "OrderStatus&Sequence_7",
        "OrderId&Sequence_7",
        "popUpMessage&Sequence_7",
        "Counter&Sequence_9",
        "table&Sequence_10",
        "Store&Sequence_10",
        "ItemCode&Sequence_10",
        "BillingDate&Sequence_10",
        "msg&Sequence_11"
      ],
      "ArgumentsSectionElementsOrder": [
        "IO_Present_URL",
        "I_DataRow",
        "O_Output_msg",
        "O_Ver_Result_Bool"
      ],
      "ConstantsSectionElementsOrder": [],
      "AddedNamespaces": null
    },
    {
      "Path": "GS_OP_007_Sub_Item_Pricing Method_Original_Item.xaml",
      "SortBy": 0,
      "VariablesSectionElementsOrder": [
        "SubItem&Sequence_1",
        "Sub_Item&Sequence_1",
        "Pricing_Method&Sequence_1",
        "price&Sequence_5",
        "BillingDate&Sequence_1",
        "confirmation_id&Sequence_1",
        "Sub_Item1&Sequence_1",
        "getText&Sequence_1",
        "ItemCode&Sequence_5",
        "Datatable&Sequence_5",
        "table&Sequence_5",
        "SellValue&Sequence_5",
        "Sell_D&Sequence_5",
        "FoundElement&Sequence_5",
        "Warning&Sequence_5",
        "text&Sequence_5",
        "Status&Sequence_5",
        "Sell_D&Sequence_6",
        "text&Sequence_6",
        "OrderStatus&Sequence_6",
        "OrderStatus&Sequence_7",
        "OrderId&Sequence_7",
        "popUpMessage&Sequence_7",
        "Counter&Sequence_9",
        "table&Sequence_10",
        "Store&Sequence_10",
        "ItemCode&Sequence_10",
        "BillingDate&Sequence_10",
        "msg&Sequence_11"
      ],
      "ArgumentsSectionElementsOrder": [
        "IO_Present_URL",
        "I_DataRow",
        "O_Output_msg",
        "O_Ver_Result_Bool"
      ],
      "ConstantsSectionElementsOrder": [],
      "AddedNamespaces": null
    },
    {
      "Path": "GS_OP_011_Test_PennyCost.xaml",
      "SortBy": 0,
      "VariablesSectionElementsOrder": [
        "Counter&Sequence_209",
        "table&Sequence_201",
        "Store&Sequence_201",
        "ItemCode&Sequence_201",
        "BillingDate&Sequence_201",
        "msg&Sequence_202",
        "confirmationID&Sequence_1",
        "BillingDate&Sequence_1",
        "confirmation_id&Sequence_1",
        "getText&Sequence_1",
        "order&Sequence_1",
        "orderid&Sequence_1",
        "Approval_Type&Sequence_1",
        "ItemCode&Sequence_128",
        "Datatable&Sequence_128",
        "table&Sequence_128",
        "SellValue&Sequence_128",
        "Sell_D&Sequence_128",
        "FoundElement&Sequence_128",
        "Warning&Sequence_128",
        "text&Sequence_128",
        "Status&Sequence_128",
        "Sell_D&Sequence_129",
        "text&Sequence_129",
        "OrderStatus&Sequence_129",
        "OrderStatus&Sequence_130",
        "OrderId&Sequence_130",
        "popUpMessage&Sequence_130",
        "Counter&Sequence_132"
      ],
      "ArgumentsSectionElementsOrder": [
        "IO_Present_URL",
        "O_Output_msg",
        "O_Ver_Result_Bool",
        "I_DataRow"
      ],
      "ConstantsSectionElementsOrder": [],
      "AddedNamespaces": null
    },
    {
      "Path": "GS_OP_012_Test_NoSellPrice.xaml",
      "SortBy": 0,
      "VariablesSectionElementsOrder": [
        "Counter&Sequence_265",
        "table&Sequence_257",
        "Store&Sequence_257",
        "ItemCode&Sequence_257",
        "BillingDate&Sequence_257",
        "msg&Sequence_258",
        "Errormsg&Sequence_245",
        "confirmationID&Sequence_245",
        "confirmation_id&Sequence_245",
        "BillingDate&Sequence_245",
        "getText&Sequence_245",
        "Approval_Type&Sequence_245",
        "order&Sequence_245",
        "orderid&Sequence_245",
        "ItemCode&Sequence_180",
        "Datatable&Sequence_180",
        "table&Sequence_180",
        "SellValue&Sequence_180",
        "Sell_D&Sequence_180",
        "FoundElement&Sequence_180",
        "Warning&Sequence_180",
        "text&Sequence_180",
        "Status&Sequence_180",
        "Sell_D&Sequence_181",
        "text&Sequence_181",
        "OrderStatus&Sequence_181",
        "OrderStatus&Sequence_182",
        "OrderId&Sequence_182",
        "popUpMessage&Sequence_182",
        "Counter&Sequence_184"
      ],
      "ArgumentsSectionElementsOrder": [
        "IO_Present_URL",
        "O_Output_msg",
        "O_Ver_Result_Bool",
        "I_DataRow"
      ],
      "ConstantsSectionElementsOrder": [],
      "AddedNamespaces": null
    },
    {
      "Path": "GS_OP_010_Test_SellPrice_Tolerance.xaml",
      "SortBy": 0,
      "VariablesSectionElementsOrder": [
        "Counter&Sequence_174",
        "Counter&Sequence_1",
        "Approval_Type&Sequence_1",
        "getText&Sequence_1",
        "confirmation_id&Sequence_1",
        "BillingDate&Sequence_1",
        "order&Sequence_1",
        "orderid&Sequence_1",
        "Status&Sequence_1",
        "ItemCode&Sequence_65",
        "Datatable&Sequence_65",
        "table&Sequence_65",
        "SellValue&Sequence_65",
        "Sell_D&Sequence_65",
        "FoundElement&Sequence_65",
        "Warning&Sequence_65",
        "text&Sequence_65",
        "status&Sequence_65",
        "Sell_D&Sequence_66",
        "text&Sequence_66",
        "OrderStatus&Sequence_66",
        "OrderStatus&Sequence_68",
        "OrderId&Sequence_68",
        "popUpMessage&Sequence_68",
        "ItemDescription&Sequence_69",
        "Counter&Sequence_139",
        "table&Sequence_165",
        "Store&Sequence_165",
        "ItemCode&Sequence_165",
        "BillingDate&Sequence_165",
        "msg&Sequence_166"
      ],
      "ArgumentsSectionElementsOrder": [
        "IO_Present_URL",
        "O_Output_msg",
        "O_Ver_Result_Bool",
        "I_DataRow"
      ],
      "ConstantsSectionElementsOrder": [],
      "AddedNamespaces": null
    },
    {
      "Path": "GS_OP_007_Sub_Item_Pricing Method_Original_Item_Old.xaml",
      "SortBy": 0,
      "VariablesSectionElementsOrder": [
        "BillingDate&Sequence_1",
        "confirmation_id&Sequence_1",
        "SubItem&Sequence_1",
        "Sub_Item&Sequence_1",
        "Sub_Item1&Sequence_1",
        "getText&Sequence_1",
        "Pricing_Method&Sequence_1",
        "ItemCode&Sequence_5",
        "Datatable&Sequence_5",
        "table&Sequence_5",
        "SellValue&Sequence_5",
        "Sell_D&Sequence_5",
        "FoundElement&Sequence_5",
        "Warning&Sequence_5",
        "text&Sequence_5",
        "Status&Sequence_5",
        "price&Sequence_5",
        "Sell_D&Sequence_6",
        "text&Sequence_6",
        "OrderStatus&Sequence_6",
        "OrderStatus&Sequence_7",
        "OrderId&Sequence_7",
        "popUpMessage&Sequence_7",
        "ItemDescription&Sequence_8",
        "Counter&Sequence_9",
        "table&Sequence_10",
        "Store&Sequence_10",
        "ItemCode&Sequence_10",
        "BillingDate&Sequence_10",
        "msg&Sequence_11"
      ],
      "ArgumentsSectionElementsOrder": [
        "IO_Present_URL",
        "I_DataRow",
        "O_Output_msg",
        "O_Ver_Result_Bool"
      ],
      "ConstantsSectionElementsOrder": [],
      "AddedNamespaces": null
    },
    {
      "Path": "GS_OP_006_Sub item_Line level_Rather_than_Original Item_Old.xaml",
      "SortBy": 0,
      "VariablesSectionElementsOrder": [
        "BillingDate&Sequence_1",
        "confirmation_id&Sequence_1",
        "getText&Sequence_1",
        "Sub_Item1&Sequence_1",
        "ItemCode&Sequence_5",
        "Datatable&Sequence_5",
        "table&Sequence_5",
        "SellValue&Sequence_5",
        "Sell_D&Sequence_5",
        "FoundElement&Sequence_5",
        "Warning&Sequence_5",
        "text&Sequence_5",
        "Status&Sequence_5",
        "SubItem&Sequence_5",
        "Sub_Item&Sequence_5",
        "Sell_D&Sequence_6",
        "text&Sequence_6",
        "OrderStatus&Sequence_6",
        "OrderStatus&Sequence_7",
        "OrderId&Sequence_7",
        "popUpMessage&Sequence_7",
        "ItemDescription&Sequence_8",
        "Counter&Sequence_9",
        "table&Sequence_10",
        "Store&Sequence_10",
        "ItemCode&Sequence_10",
        "BillingDate&Sequence_10",
        "msg&Sequence_11"
      ],
      "ArgumentsSectionElementsOrder": [
        "IO_Present_URL",
        "I_DataRow",
        "O_Output_msg",
        "O_Ver_Result_Bool"
      ],
      "ConstantsSectionElementsOrder": [],
      "AddedNamespaces": null
    },
    {
      "Path": "DivCom.xaml",
      "SortBy": 0,
      "VariablesSectionElementsOrder": [
        "Company&Sequence_1",
        "Division&Sequence_1",
        "OrderScreen&Sequence_1",
        "Array&Sequence_2"
      ],
      "ArgumentsSectionElementsOrder": [
        "IO_Present_URL",
        "I_Division",
        "I_Company",
        "I_OrderType"
      ],
      "ConstantsSectionElementsOrder": [],
      "AddedNamespaces": null
    },
    {
      "Path": "Driver.xaml",
      "SortBy": 0,
      "VariablesSectionElementsOrder": [
        "ConfigFile&Sequence_1",
        "ConfigSheet&Sequence_1",
        "TestDataFile&Sequence_1",
        "TestDataSheet&Sequence_1",
        "configDT&Sequence_1",
        "Out_Config&Sequence_1",
        "Testdata_DT&Sequence_1",
        "EnvUrlName&Sequence_1",
        "URL&Sequence_1",
        "UserName&Sequence_1",
        "PassWord&Sequence_1",
        "present_url&Sequence_1",
        "Exception&Sequence_1",
        "Output_msg&Sequence_1",
        "Ver_Result_Bool&Sequence_1",
        "Start_Time&Sequence_1",
        "DataRow&Sequence_1",
        "end_time&Sequence_1",
        "strRootDirectory&Sequence_2",
        "Seconds&Sequence_19"
      ],
      "ArgumentsSectionElementsOrder": [],
      "ConstantsSectionElementsOrder": [],
      "AddedNamespaces": null
    }
  ]
}